{
  "N_candidate_days": 1044,
  "unique_tickers": 147,
  "censored_missing_rank_n": 0,
  "censored_missing_rank_pct": 0.0,
  "censoring_investigate": false,
  "excluded_price_data": 0,
  "H1a_paired_diff_pp": -4.353,
  "H1a_ci_lo_pp": -6.32,
  "H1a_ci_hi_pp": -2.256,
  "H1a_pass": false,
  "baseline_mean_pct": 7.233,
  "rank_50_paired_diff_pp": -4.353,
  "rank_50_early_exit_pct": 98.08,
  "rank_50_hold_mean_d": 8.23,
  "rank_25_paired_diff_pp": -4.939,
  "rank_25_early_exit_pct": 98.95,
  "rank_25_hold_mean_d": 6.94,
  "rank_100_paired_diff_pp": -3.494,
  "rank_100_early_exit_pct": 93.97,
  "rank_100_hold_mean_d": 9.85,
  "surv50_after_5d_pct": 61.49,
  "surv50_after_10d_pct": 17.72,
  "surv50_after_15d_pct": 5.27,
  "surv50_after_20d_pct": 1.63,
  "surv50_loss_pct": 98.37,
  "surv50_median_time_to_loss_d": 7.0
}